upstage_des/__init__.py
upstage_des/_version.py
upstage_des/actor.py
upstage_des/api.py
upstage_des/base.py
upstage_des/constants.py
upstage_des/data_types.py
upstage_des/events.py
upstage_des/math_utils.py
upstage_des/nucleus.py
upstage_des/py.typed
upstage_des/routines.py
upstage_des/state_proxies.py
upstage_des/state_sharing.py
upstage_des/states.py
upstage_des/task.py
upstage_des/task_network.py
upstage_des/type_help.py
upstage_des/utils.py
upstage_des/communications/__init__.py
upstage_des/communications/comms.py
upstage_des/communications/processes.py
upstage_des/communications/routing.py
upstage_des/data_utils/__init__.py
upstage_des/data_utils/data_recorder.py
upstage_des/data_utils/data_utils.py
upstage_des/geography/__init__.py
upstage_des/geography/conversions.py
upstage_des/geography/geo_types.py
upstage_des/geography/intersections.py
upstage_des/geography/spherical.py
upstage_des/geography/wgs84.py
upstage_des/motion/__init__.py
upstage_des/motion/cartesian_model.py
upstage_des/motion/geodetic_model.py
upstage_des/motion/great_circle_calcs.py
upstage_des/motion/motion.py
upstage_des/motion/stepped_motion.py
upstage_des/resources/__init__.py
upstage_des/resources/container.py
upstage_des/resources/monitoring.py
upstage_des/resources/reserve.py
upstage_des/resources/sorted.py
upstage_des/test/__init__.py
upstage_des/test/conftest.py
upstage_des/test/test_actor.py
upstage_des/test/test_api.py
upstage_des/test/test_base.py
upstage_des/test/test_comms.py
upstage_des/test/test_container.py
upstage_des/test/test_data_reporting.py
upstage_des/test/test_data_types.py
upstage_des/test/test_event.py
upstage_des/test/test_great_circle_calcs.py
upstage_des/test/test_integration.py
upstage_des/test/test_knowledge.py
upstage_des/test/test_locations.py
upstage_des/test/test_monitoring.py
upstage_des/test/test_motion.py
upstage_des/test/test_network_qol.py
upstage_des/test/test_nucleus.py
upstage_des/test/test_parallel_task_network.py
upstage_des/test/test_routines.py
upstage_des-0.4.0.dist-info/licenses/LICENSE
upstage_des-0.4.0.dist-info/WHEEL
upstage_des-0.4.0.dist-info/METADATA
upstage_des-0.4.0.dist-info/RECORD
