Metadata-Version: 2.4
Name: upstage-des
Version: 0.4.0
Summary: A library for behavior-driven discrete event simulation.
Keywords: agent based modeling,agents,behavior modeling,discrete event simulation,modeling,operations,simpy,simulation
Author-email: James Arruda <James.Arruda@gtri.gatech.edu>
Requires-Python: >=3.11
Classifier: Development Status :: 4 - Beta
Classifier: Intended Audience :: Developers
Classifier: Intended Audience :: Education
Classifier: Intended Audience :: Science/Research
Classifier: License :: OSI Approved :: BSD License
Classifier: Natural Language :: English
Classifier: Operating System :: OS Independent
Classifier: Programming Language :: Python :: 3 :: Only
Classifier: Programming Language :: Python :: 3.11
Classifier: Programming Language :: Python :: 3.12
Classifier: Programming Language :: Python :: 3.13
Classifier: Topic :: Scientific/Engineering
Classifier: Topic :: Software Development :: Libraries :: Python Modules
License-File: LICENSE
Requires-Dist: simpy>=4
Requires-Dist: myst-parser ; extra == "docs"
Requires-Dist: pydata-sphinx-theme ; extra == "docs"
Requires-Dist: sphinx>=7 ; extra == "docs"
Requires-Dist: mypy ; extra == "lint"
Requires-Dist: pyproject-fmt>=2.5 ; extra == "lint"
Requires-Dist: ruff>=0.6 ; extra == "lint"
Requires-Dist: ssort>=0.12 ; extra == "lint"
Requires-Dist: pytest ; extra == "test"
Requires-Dist: pytest-cov ; extra == "test"
Requires-Dist: pytest-html ; extra == "test"
Requires-Dist: pytest-json-report ; extra == "test"
Requires-Dist: pytest-xdist ; extra == "test"
Project-URL: Bug Tracker, https://github.com/gtri/upstage/issues
Project-URL: Documentation, https://gtri.github.io/upstage
Project-URL: Source, https://github.com/gtri/upstage
Provides-Extra: docs
Provides-Extra: lint
Provides-Extra: test
